{
  "name": "vscode",
  "version": "1.121.0",
  "description": "Install Visual Studio Code with extensions for development.",
  "order": 1900,
  "command": "powershell.exe -ExecutionPolicy Bypass -NoProfile -NonInteractive -File \".\\provide-vscode.ps1\" -AssetsRoot \".\" -InstallRoot \"C:\\Program Files\\Microsoft VS Code\"",
  "commandfiles": [
    "provide-vscode.ps1",
    "assets/VSCodeUserSetup-x64-1.121.0.exe"
  ],
  "verify": "powershell.exe -ExecutionPolicy Bypass -NoProfile -NonInteractive -Command \"$u = Join-Path $env:LOCALAPPDATA 'Programs\\Microsoft VS Code\\Code.exe'; $s = 'C:\\\\Program Files\\\\Microsoft VS Code\\\\Code.exe'; $log = Join-Path (Join-Path $env:SystemDrive 'MAST') 'logs\\\\verify\\\\vscode-verify.log'; $smoke = Join-Path (Join-Path $env:SystemDrive 'MAST') 'logs\\\\smoke\\\\vscode-smoke.txt'; if ((Test-Path -LiteralPath $u) -or (Test-Path -LiteralPath $s)) { Set-Content -Path $log -Value 'VSCode installed successfully'; Set-Content -Path $smoke -Value 'vscode_ok' } else { 'VSCode executable not found (UserSetup or system path)' | Out-File -FilePath $log -Encoding UTF8; exit 1 }\""
}

